LICENSE
MANIFEST.in
README.md
RELEASE.md
pyproject.toml
setup.cfg
setup.py
versioneer.py
LICENSES/DATEUTIL_LICENSE
LICENSES/HAVEN_LICENSE
LICENSES/HAVEN_MIT
LICENSES/KLIB_LICENSE
LICENSES/MUSL_LICENSE
LICENSES/NUMPY_LICENSE
LICENSES/OTHER
LICENSES/PACKAGING_LICENSE
LICENSES/PSF_LICENSE
LICENSES/PYUPGRADE_LICENSE
LICENSES/SAS7BDAT_LICENSE
LICENSES/SCIPY_LICENSE
LICENSES/ULTRAJSON_LICENSE
LICENSES/XARRAY_LICENSE
doc/make.py
doc/_templates/autosummary/accessor.rst
doc/_templates/autosummary/accessor_attribute.rst
doc/_templates/autosummary/accessor_callable.rst
doc/_templates/autosummary/accessor_method.rst
doc/_templates/autosummary/class.rst
doc/_templates/autosummary/class_without_autosummary.rst
doc/cheatsheet/README.txt
doc/data/iris.data
doc/source/conf.py
doc/source/ecosystem.rst
doc/source/index.rst.template
doc/source/_static/index_api.svg
doc/source/_static/index_contribute.svg
doc/source/_static/index_getting_started.svg
doc/source/_static/index_user_guide.svg
doc/source/_static/logo_r.svg
doc/source/_static/logo_sas.svg
doc/source/_static/logo_sql.svg
doc/source/_static/logo_stata.svg
doc/source/_static/question_mark_noback.svg
doc/source/_static/stub
doc/source/_static/css/getting_started.css
doc/source/_static/css/pandas.css
doc/source/_static/schemas/01_table_dataframe.svg
doc/source/_static/schemas/01_table_series.svg
doc/source/_static/schemas/02_io_readwrite.svg
doc/source/_static/schemas/03_subset_columns.svg
doc/source/_static/schemas/03_subset_columns_rows.svg
doc/source/_static/schemas/03_subset_rows.svg
doc/source/_static/schemas/04_plot_overview.svg
doc/source/_static/schemas/05_newcolumn_1.svg
doc/source/_static/schemas/05_newcolumn_2.svg
doc/source/_static/schemas/05_newcolumn_3.svg
doc/source/_static/schemas/06_aggregate.svg
doc/source/_static/schemas/06_groupby.svg
doc/source/_static/schemas/06_groupby_agg_detail.svg
doc/source/_static/schemas/06_groupby_select_detail.svg
doc/source/_static/schemas/06_reduction.svg
pdplus.egg-info/PKG-INFO
pdplus.egg-info/SOURCES.txt
pdplus.egg-info/dependency_links.txt
pdplus.egg-info/not-zip-safe
pdplus.egg-info/requires.txt
pdplus.egg-info/top_level.txt