Metadata-Version: 2.1
Name: pdplus
Version: 2401
Summary: an new data analysis library add many feature,add duckdb sql functions.so calls: pandas plus
Home-page: https://wangnz.v6.army:5000/
Author: wangnz
Author-email: wangnz99@qq.com
License: BSD-3-Clause
Project-URL: Documentation, https://wangnz.v6.army:5000/
Project-URL: Source Code, https://wangnz.v6.army:5000/
Platform: any
Classifier: Development Status :: 5 - Production/Stable
Classifier: Environment :: Console
Classifier: Intended Audience :: Science/Research
Classifier: License :: OSI Approved :: BSD License
Classifier: Operating System :: OS Independent
Classifier: Programming Language :: SQL
Classifier: Programming Language :: Python
Classifier: Topic :: Scientific/Engineering
Requires-Python: >=3.8
Provides-Extra: test
License-File: LICENSE
